Fragment/__init__.py
Fragment/core.py
Fragment/models.py
Fragment/premium/__init__.py
Fragment/premium/premium_cur_ammout.py
Fragment/stars/__init__.py
Fragment/stars/pay_info.py
Fragment/stars/pay_init.py
Fragment/stars/stars_cur_ammout.py
Fragment/ton/__init__.py
Fragment/ton/lite_servers.py
Fragment/ton/ton_transfer.py
Fragment/ton/v4r2_send.py
Fragment/ton/wallet_balance.py
Fragment/ton/wallet/__init__.py
Fragment/ton/wallet/v4r2/__init__.py
Fragment/users/__init__.py
Fragment/users/profile.py
Fragment/users/session.py
Fragment/utils/__init__.py
Fragment/utils/decoder.py
Fragment/utils/nick_to_hash.py
fragment_py2-0.0.2.dist-info/licenses/LICENSE
fragment_py2-0.0.2.dist-info/METADATA
fragment_py2-0.0.2.dist-info/WHEEL
fragment_py2-0.0.2.dist-info/top_level.txt
fragment_py2-0.0.2.dist-info/RECORD
